hra_glb_mesh_collisions/__about__.py
hra_glb_mesh_collisions/__init__.py
hra_glb_mesh_collisions-0.1.1.dist-info/METADATA
hra_glb_mesh_collisions-0.1.1.dist-info/WHEEL
hra_glb_mesh_collisions-0.1.1.dist-info/entry_points.txt
hra_glb_mesh_collisions-0.1.1.dist-info/licenses/LICENSE
hra_glb_mesh_collisions-0.1.1.dist-info/RECORD
