Metadata-Version: 2.3
Name: hra-glb-mesh-collisions
Version: 0.1.1
Summary: A command-line interface to extract mesh-mesh collision information from GLB files
Project-URL: Homepage, https://github.com/hubmapconsortium/hra-glb-mesh-collisions
Project-URL: Documentation, https://github.com/hubmapconsortium/hra-glb-mesh-collisions
Project-URL: Repository, https://github.com/hubmapconsortium/hra-glb-mesh-collisions.git
Project-URL: Issues, https://github.com/hubmapconsortium/hra-glb-mesh-collisions/issues
Project-URL: Changelog, https://github.com/hubmapconsortium/hra-glb-mesh-collisions/blob/main/CHANGELOG.md
Author-email: Chenran Li <chenran.li@stonybrook.edu>, "Bruce W. Herr II" <bherr@iu.edu>
Maintainer-email: "Bruce W. Herr II" <bherr@iu.edu>
License-Expression: MIT
License-File: LICENSE
Keywords: collision detection,glb
Requires-Python: >=3.8
Requires-Dist: numpy<2
Requires-Dist: pygltflib
Requires-Dist: python-fcl
Requires-Dist: scipy
Requires-Dist: trimesh
